ectoconfig/__init__.py
ectoconfig/click.py
ectoconfig/config.py
ectoconfig/dotenv.py
ectoconfig/env.py
ectoconfig/file.py
ectoconfig-0.1.7.dist-info/METADATA
ectoconfig-0.1.7.dist-info/RECORD
ectoconfig-0.1.7.dist-info/WHEEL
ectoconfig-0.1.7.dist-info/top_level.txt
ectoconfig-0.1.7.dist-info/zip-safe
